JIVLearningPackage/__init__.py
JIVLearningPackage/abcd.py
JIVLearningPackage/numbers.py
JIVLearningPackage-1.1.1.dist-info/LICENSE
JIVLearningPackage-1.1.1.dist-info/METADATA
JIVLearningPackage-1.1.1.dist-info/WHEEL
JIVLearningPackage-1.1.1.dist-info/top_level.txt
JIVLearningPackage-1.1.1.dist-info/RECORD
