Metadata-Version: 2.1
Name: JIVLearningPackage
Version: 1.1.1
Summary: Learning process
Home-page: UNKNOWN
Author-email: m.johnmarshal@gmail.com
License: UNKNOWN
Platform: UNKNOWN
